tests/test_generators.py
tests/test_meta_generators.py
tsg/__init__.py
tsg/generators.py
tsg/meta_generators.py
tsg/modifiers.py
tsg_lib-0.2.2.dist-info/METADATA
tsg_lib-0.2.2.dist-info/WHEEL
tsg_lib-0.2.2.dist-info/top_level.txt
tsg_lib-0.2.2.dist-info/RECORD
