Metadata-Version: 2.4
Name: tsg-lib
Version: 0.2.2
Summary: A modular library for synthetic time series generation.
Author-email: Mathis Jander <mathis.jander@utwente.nl>, Jens Reil <jens.reil@bfh.ch>
License: MIT
Project-URL: Homepage, https://github.com/MSCA-DN-Digital-Finance/tsg
Classifier: Programming Language :: Python :: 3
Classifier: License :: OSI Approved :: MIT License
Classifier: Operating System :: OS Independent
Requires-Python: >=3.8
Requires-Dist: numpy
